README.rst
setup.py
camltex/__init__.py
camltex/command_line.py
camltex/ocaml_eval.py
camltex/ocaml_writer.py
camltex.egg-info/PKG-INFO
camltex.egg-info/SOURCES.txt
camltex.egg-info/dependency_links.txt
camltex.egg-info/entry_points.txt
camltex.egg-info/not-zip-safe
camltex.egg-info/requires.txt
camltex.egg-info/top_level.txt
tests/__init__.py