Metadata-Version: 1.0
Name: camltex
Version: 0.1.2
Summary: CLI for processing embedded OCaml.
Home-page: http://github.com/cs51/camltex
Author: Sam Green
Author-email: cs51heads@gmail.com
License: MIT
Platform: UNKNOWN
